build/lib/build/lib/build/lib/build/lib/build/lib/build/lib/build/lib/build/lib/build/lib/build/lib/build/lib/build/lib/build/lib/build/lib/build/lib/build/lib/build/lib/build/lib/sumo_pts/__init__.py
build/lib/build/lib/build/lib/build/lib/build/lib/build/lib/build/lib/build/lib/build/lib/build/lib/build/lib/build/lib/build/lib/build/lib/build/lib/build/lib/build/lib/build/lib/sumo_pts/simulation.py
build/lib/build/lib/build/lib/build/lib/build/lib/build/lib/build/lib/build/lib/build/lib/build/lib/build/lib/build/lib/build/lib/build/lib/build/lib/build/lib/build/lib/sumo_pts/__init__.py
build/lib/build/lib/build/lib/build/lib/build/lib/build/lib/build/lib/build/lib/build/lib/build/lib/build/lib/build/lib/build/lib/build/lib/build/lib/build/lib/build/lib/sumo_pts/simulation.py
build/lib/build/lib/build/lib/build/lib/build/lib/build/lib/build/lib/build/lib/build/lib/build/lib/build/lib/build/lib/build/lib/build/lib/build/lib/build/lib/build/lib/sumo_pts/trips/__init__.py
build/lib/build/lib/build/lib/build/lib/build/lib/build/lib/build/lib/build/lib/build/lib/build/lib/build/lib/build/lib/build/lib/build/lib/build/lib/build/lib/build/lib/sumo_pts/trips/trips.py
build/lib/build/lib/build/lib/build/lib/build/lib/build/lib/build/lib/build/lib/build/lib/build/lib/build/lib/build/lib/build/lib/build/lib/build/lib/build/lib/sumo_pts/__init__.py
build/lib/build/lib/build/lib/build/lib/build/lib/build/lib/build/lib/build/lib/build/lib/build/lib/build/lib/build/lib/build/lib/build/lib/build/lib/build/lib/sumo_pts/simulation.py
build/lib/build/lib/build/lib/build/lib/build/lib/build/lib/build/lib/build/lib/build/lib/build/lib/build/lib/build/lib/build/lib/build/lib/build/lib/build/lib/sumo_pts/trips/__init__.py
build/lib/build/lib/build/lib/build/lib/build/lib/build/lib/build/lib/build/lib/build/lib/build/lib/build/lib/build/lib/build/lib/build/lib/build/lib/build/lib/sumo_pts/trips/trips.py
sumo_pts-0.2.dist-info/LICENSE
sumo_pts-0.2.dist-info/METADATA
sumo_pts-0.2.dist-info/WHEEL
sumo_pts-0.2.dist-info/top_level.txt
sumo_pts-0.2.dist-info/RECORD
