Metadata-Version: 2.1
Name: sumo_pts
Version: 0.2
Summary: A Python interface for simulating public transport systems using SUMO.
Home-page: https://github.com/itsAliSali/sumo_pts
Author: itsAliSali
Author-email: Ali <ali.salimian@rwth-aachen.de>
License: Eclipse Public License - v 2.0
Requires-Python: >=3.8
License-File: LICENSE
